varg/__init__.py
varg/__main__.py
varg/cli/__init__.py
varg/cli/compare.py
varg/cli/root.py
varg/resources/__init__.py
varg/resources/compare_fields.py
varg/utils/__init__.py
varg/utils/compare.py
varg/utils/compare_mixin.py
varg/utils/vcf_handler.py
varg/utils/write_report.py
varg-1.6.11.dist-info/entry_points.txt
varg-1.6.11.dist-info/LICENSE
varg-1.6.11.dist-info/WHEEL
varg-1.6.11.dist-info/METADATA
varg-1.6.11.dist-info/RECORD
